{
  "segs": [
    {
      "x0": 3365.0,
      "y0": 836.0,
      "x1": 3384.0,
      "y1": 644.0,
      "len": 19.507855044582538,
      "cum_start": 0.0
    },
    {
      "x0": 3384.0,
      "y0": 644.0,
      "x1": 3392.0,
      "y1": 514.0,
      "len": 13.169106156402377,
      "cum_start": 19.507855044582538
    },
    {
      "x0": 3392.0,
      "y0": 514.0,
      "x1": 3388.0,
      "y1": 106.0,
      "len": 41.254677859891764,
      "cum_start": 32.67696120098492
    },
    {
      "x0": 3388.0,
      "y0": 106.0,
      "x1": 3363.0,
      "y1": -201.0,
      "len": 31.143381965978108,
      "cum_start": 73.93163906087668
    },
    {
      "x0": 3363.0,
      "y0": -201.0,
      "x1": 3345.0,
      "y1": -362.0,
      "len": 16.380058753521727,
      "cum_start": 105.0750210268548
    },
    {
      "x0": 3345.0,
      "y0": -362.0,
      "x1": 3328.0,
      "y1": -504.0,
      "len": 14.460079338475786,
      "cum_start": 121.45507978037651
    },
    {
      "x0": 3328.0,
      "y0": -504.0,
      "x1": 3299.0,
      "y1": -759.0,
      "len": 25.9491305839227,
      "cum_start": 135.9151591188523
    },
    {
      "x0": 3299.0,
      "y0": -759.0,
      "x1": 3294.0,
      "y1": -811.0,
      "len": 5.281945727520755,
      "cum_start": 161.864289702775
    },
    {
      "x0": 3294.0,
      "y0": -811.0,
      "x1": 3282.0,
      "y1": -994.0,
      "len": 18.542785320531454,
      "cum_start": 167.14623543029575
    },
    {
      "x0": 3282.0,
      "y0": -994.0,
      "x1": 3281.0,
      "y1": -1097.0,
      "len": 10.414774200794868,
      "cum_start": 185.6890207508272
    },
    {
      "x0": 3281.0,
      "y0": -1097.0,
      "x1": 3285.0,
      "y1": -1171.0,
      "len": 7.4930293017570095,
      "cum_start": 196.10379495162206
    },
    {
      "x0": 3285.0,
      "y0": -1171.0,
      "x1": 3296.0,
      "y1": -1249.0,
      "len": 7.964583313471704,
      "cum_start": 203.59682425337908
    },
    {
      "x0": 3296.0,
      "y0": -1249.0,
      "x1": 3312.0,
      "y1": -1314.0,
      "len": 6.768300597720593,
      "cum_start": 211.56140756685076
    },
    {
      "x0": 3312.0,
      "y0": -1314.0,
      "x1": 3385.0,
      "y1": -1464.0,
      "len": 16.867121255935604,
      "cum_start": 218.32970816457134
    },
    {
      "x0": 3385.0,
      "y0": -1464.0,
      "x1": 3432.0,
      "y1": -1520.0,
      "len": 7.392069158926155,
      "cum_start": 235.196829420507
    },
    {
      "x0": 3432.0,
      "y0": -1520.0,
      "x1": 3490.0,
      "y1": -1574.0,
      "len": 8.012572801631007,
      "cum_start": 242.58889857943313
    },
    {
      "x0": 3490.0,
      "y0": -1574.0,
      "x1": 3578.0,
      "y1": -1639.0,
      "len": 11.061680239210409,
      "cum_start": 250.60147138106416
    },
    {
      "x0": 3578.0,
      "y0": -1639.0,
      "x1": 3668.0,
      "y1": -1692.0,
      "len": 10.56050380852037,
      "cum_start": 261.66315162027456
    },
    {
      "x0": 3668.0,
      "y0": -1692.0,
      "x1": 3768.0,
      "y1": -1746.0,
      "len": 11.490956611731706,
      "cum_start": 272.2236554287949
    },
    {
      "x0": 3768.0,
      "y0": -1746.0,
      "x1": 3818.0,
      "y1": -1782.0,
      "len": 6.229529811901168,
      "cum_start": 283.7146120405266
    },
    {
      "x0": 3818.0,
      "y0": -1782.0,
      "x1": 3868.0,
      "y1": -1842.0,
      "len": 7.896908103513983,
      "cum_start": 289.9441418524278
    },
    {
      "x0": 3868.0,
      "y0": -1842.0,
      "x1": 3885.0,
      "y1": -1894.0,
      "len": 5.531533221818031,
      "cum_start": 297.84104995594174
    },
    {
      "x0": 3885.0,
      "y0": -1894.0,
      "x1": 3887.0,
      "y1": -1954.0,
      "len": 6.069942230713605,
      "cum_start": 303.3725831777598
    },
    {
      "x0": 3887.0,
      "y0": -1954.0,
      "x1": 3883.0,
      "y1": -1985.0,
      "len": 3.160381045988691,
      "cum_start": 309.44252540847344
    },
    {
      "x0": 3883.0,
      "y0": -1985.0,
      "x1": 3874.0,
      "y1": -2023.0,
      "len": 3.9484540517569915,
      "cum_start": 312.60290645446213
    },
    {
      "x0": 3874.0,
      "y0": -2023.0,
      "x1": 3855.0,
      "y1": -2075.0,
      "len": 5.597671471827676,
      "cum_start": 316.5513605062191
    },
    {
      "x0": 3855.0,
      "y0": -2075.0,
      "x1": 3803.0,
      "y1": -2165.0,
      "len": 10.509558074813905,
      "cum_start": 322.1490319780468
    },
    {
      "x0": 3803.0,
      "y0": -2165.0,
      "x1": 3764.0,
      "y1": -2203.0,
      "len": 5.505598227947018,
      "cum_start": 332.6585900528607
    },
    {
      "x0": 3764.0,
      "y0": -2203.0,
      "x1": 3724.0,
      "y1": -2229.0,
      "len": 4.823677848019725,
      "cum_start": 338.1641882808077
    },
    {
      "x0": 3724.0,
      "y0": -2229.0,
      "x1": 3645.0,
      "y1": -2257.0,
      "len": 8.474524331225945,
      "cum_start": 342.9878661288275
    },
    {
      "x0": 3645.0,
      "y0": -2257.0,
      "x1": 3588.0,
      "y1": -2266.0,
      "len": 5.8346429336082455,
      "cum_start": 351.46239046005337
    },
    {
      "x0": 3588.0,
      "y0": -2266.0,
      "x1": 3534.0,
      "y1": -2271.0,
      "len": 5.483270600055018,
      "cum_start": 357.29703339366165
    },
    {
      "x0": 3534.0,
      "y0": -2271.0,
      "x1": 3502.0,
      "y1": -2272.0,
      "len": 3.2370849701754523,
      "cum_start": 362.78030399371664
    },
    {
      "x0": 3502.0,
      "y0": -2272.0,
      "x1": 3380.0,
      "y1": -2272.0,
      "len": 12.335364791226944,
      "cum_start": 366.0173889638921
    },
    {
      "x0": 3380.0,
      "y0": -2272.0,
      "x1": 3168.0,
      "y1": -2250.0,
      "len": 21.550332496165787,
      "cum_start": 378.352753755119
    },
    {
      "x0": 3168.0,
      "y0": -2250.0,
      "x1": 3038.0,
      "y1": -2221.0,
      "len": 13.467321084631472,
      "cum_start": 399.90308625128483
    },
    {
      "x0": 3038.0,
      "y0": -2221.0,
      "x1": 2831.0,
      "y1": -2159.0,
      "len": 21.848320382603582,
      "cum_start": 413.3704073359163
    },
    {
      "x0": 2831.0,
      "y0": -2159.0,
      "x1": 2741.0,
      "y1": -2129.0,
      "len": 9.592093895735545,
      "cum_start": 435.2187277185199
    },
    {
      "x0": 2741.0,
      "y0": -2129.0,
      "x1": 2628.0,
      "y1": -2090.0,
      "len": 12.086714980611452,
      "cum_start": 444.8108216142554
    },
    {
      "x0": 2628.0,
      "y0": -2090.0,
      "x1": 2523.0,
      "y1": -2049.0,
      "len": 11.397158607693694,
      "cum_start": 456.8975365948669
    },
    {
      "x0": 2523.0,
      "y0": -2049.0,
      "x1": 2386.0,
      "y1": -1987.0,
      "len": 15.20446901894703,
      "cum_start": 468.2946952025606
    },
    {
      "x0": 2386.0,
      "y0": -1987.0,
      "x1": 2247.0,
      "y1": -1913.0,
      "len": 15.921784359655529,
      "cum_start": 483.4991642215076
    },
    {
      "x0": 2247.0,
      "y0": -1913.0,
      "x1": 2120.0,
      "y1": -1834.0,
      "len": 15.122554512545017,
      "cum_start": 499.4209485811631
    },
    {
      "x0": 2120.0,
      "y0": -1834.0,
      "x1": 1993.0,
      "y1": -1749.0,
      "len": 15.451576790893093,
      "cum_start": 514.5435030937081
    },
    {
      "x0": 1993.0,
      "y0": -1749.0,
      "x1": 1877.0,
      "y1": -1667.0,
      "len": 14.363250923593444,
      "cum_start": 529.9950798846012
    },
    {
      "x0": 1877.0,
      "y0": -1667.0,
      "x1": 1771.0,
      "y1": -1589.0,
      "len": 13.306569618366025,
      "cum_start": 544.3583308081946
    },
    {
      "x0": 1771.0,
      "y0": -1589.0,
      "x1": 1567.0,
      "y1": -1431.0,
      "len": 26.089398238409114,
      "cum_start": 557.6649004265606
    },
    {
      "x0": 1567.0,
      "y0": -1431.0,
      "x1": 1480.0,
      "y1": -1362.0,
      "len": 11.227258056503011,
      "cum_start": 583.7542986649697
    },
    {
      "x0": 1480.0,
      "y0": -1362.0,
      "x1": 1351.0,
      "y1": -1256.0,
      "len": 16.88166135813433,
      "cum_start": 594.9815567214728
    },
    {
      "x0": 1351.0,
      "y0": -1256.0,
      "x1": 1253.0,
      "y1": -1178.0,
      "len": 12.66414740780127,
      "cum_start": 611.8632180796071
    },
    {
      "x0": 1253.0,
      "y0": -1178.0,
      "x1": 1041.0,
      "y1": -1003.0,
      "len": 27.79482885718904,
      "cum_start": 624.5273654874084
    },
    {
      "x0": 1041.0,
      "y0": -1003.0,
      "x1": 948.0,
      "y1": -916.0,
      "len": 12.876291938244567,
      "cum_start": 652.3221943445974
    },
    {
      "x0": 948.0,
      "y0": -916.0,
      "x1": 860.0,
      "y1": -816.0,
      "len": 13.468459697319796,
      "cum_start": 665.1984862828419
    },
    {
      "x0": 860.0,
      "y0": -816.0,
      "x1": 816.0,
      "y1": -756.0,
      "len": 7.522985198903609,
      "cum_start": 678.6669459801617
    },
    {
      "x0": 816.0,
      "y0": -756.0,
      "x1": 765.0,
      "y1": -658.0,
      "len": 11.17020281345136,
      "cum_start": 686.1899311790653
    },
    {
      "x0": 765.0,
      "y0": -658.0,
      "x1": 750.0,
      "y1": -609.0,
      "len": 5.181309408611541,
      "cum_start": 697.3601339925167
    },
    {
      "x0": 750.0,
      "y0": -609.0,
      "x1": 742.0,
      "y1": -528.0,
      "len": 8.229720919009358,
      "cum_start": 702.5414434011282
    },
    {
      "x0": 742.0,
      "y0": -528.0,
      "x1": 748.0,
      "y1": -451.0,
      "len": 7.809035383181184,
      "cum_start": 710.7711643201375
    },
    {
      "x0": 748.0,
      "y0": -451.0,
      "x1": 759.0,
      "y1": -382.0,
      "len": 7.064656563305442,
      "cum_start": 718.5801997033187
    },
    {
      "x0": 759.0,
      "y0": -382.0,
      "x1": 769.0,
      "y1": -202.0,
      "len": 18.227782891935203,
      "cum_start": 725.6448562666242
    },
    {
      "x0": 769.0,
      "y0": -202.0,
      "x1": 748.0,
      "y1": -49.0,
      "len": 15.614797566962206,
      "cum_start": 743.8726391585594
    },
    {
      "x0": 748.0,
      "y0": -49.0,
      "x1": 692.0,
      "y1": 104.0,
      "len": 16.473410908055563,
      "cum_start": 759.4874367255215
    },
    {
      "x0": 692.0,
      "y0": 104.0,
      "x1": 668.0,
      "y1": 143.0,
      "len": 4.630110777937549,
      "cum_start": 775.9608476335771
    },
    {
      "x0": 668.0,
      "y0": 143.0,
      "x1": 611.0,
      "y1": 223.0,
      "len": 9.931922449713761,
      "cum_start": 780.5909584115147
    },
    {
      "x0": 611.0,
      "y0": 223.0,
      "x1": 561.0,
      "y1": 287.0,
      "len": 8.21168894489359,
      "cum_start": 790.5228808612285
    },
    {
      "x0": 561.0,
      "y0": 287.0,
      "x1": 435.0,
      "y1": 443.0,
      "len": 20.275426737333657,
      "cum_start": 798.7345698061221
    },
    {
      "x0": 435.0,
      "y0": 443.0,
      "x1": 303.0,
      "y1": 606.0,
      "len": 21.20723046391275,
      "cum_start": 819.0099965434557
    },
    {
      "x0": 303.0,
      "y0": 606.0,
      "x1": 165.0,
      "y1": 768.0,
      "len": 21.517099967532403,
      "cum_start": 840.2172270073685
    },
    {
      "x0": 165.0,
      "y0": 768.0,
      "x1": 8.0,
      "y1": 926.0,
      "len": 22.52111618152931,
      "cum_start": 861.7343269749009
    },
    {
      "x0": 8.0,
      "y0": 926.0,
      "x1": -128.0,
      "y1": 1044.0,
      "len": 18.205334874930855,
      "cum_start": 884.2554431564301
    },
    {
      "x0": -128.0,
      "y0": 1044.0,
      "x1": -294.0,
      "y1": 1177.0,
      "len": 21.506882525541418,
      "cum_start": 902.4607780313611
    },
    {
      "x0": -294.0,
      "y0": 1177.0,
      "x1": -358.0,
      "y1": 1227.0,
      "len": 8.21168894489359,
      "cum_start": 923.9676605569024
    },
    {
      "x0": -358.0,
      "y0": 1227.0,
      "x1": -555.0,
      "y1": 1397.0,
      "len": 26.309667922034635,
      "cum_start": 932.179349501796
    },
    {
      "x0": -555.0,
      "y0": 1397.0,
      "x1": -584.0,
      "y1": 1426.0,
      "len": 4.146724306168922,
      "cum_start": 958.4890174238307
    },
    {
      "x0": -584.0,
      "y0": 1426.0,
      "x1": -685.0,
      "y1": 1553.0,
      "len": 16.40656245893462,
      "cum_start": 962.6357417299995
    },
    {
      "x0": -685.0,
      "y0": 1553.0,
      "x1": -760.0,
      "y1": 1687.0,
      "len": 15.5264895658568,
      "cum_start": 979.0423041889342
    },
    {
      "x0": -760.0,
      "y0": 1687.0,
      "x1": -820.0,
      "y1": 1831.0,
      "len": 15.773089405175437,
      "cum_start": 994.568793754791
    },
    {
      "x0": -820.0,
      "y0": 1831.0,
      "x1": -873.0,
      "y1": 1988.0,
      "len": 16.754312707591644,
      "cum_start": 1010.3418831599665
    },
    {
      "x0": -873.0,
      "y0": 1988.0,
      "x1": -925.0,
      "y1": 2200.0,
      "len": 22.070618541485622,
      "cum_start": 1027.0961958675582
    },
    {
      "x0": -925.0,
      "y0": 2200.0,
      "x1": -938.0,
      "y1": 2340.0,
      "len": 14.216232493592111,
      "cum_start": 1049.1668144090438
    },
    {
      "x0": -938.0,
      "y0": 2340.0,
      "x1": -944.0,
      "y1": 2560.0,
      "len": 22.25237150481307,
      "cum_start": 1063.383046902636
    },
    {
      "x0": -944.0,
      "y0": 2560.0,
      "x1": -942.0,
      "y1": 2693.0,
      "len": 13.449090171765084,
      "cum_start": 1085.635418407449
    },
    {
      "x0": -942.0,
      "y0": 2693.0,
      "x1": -938.0,
      "y1": 2840.0,
      "len": 14.868605020168909,
      "cum_start": 1099.084508579214
    },
    {
      "x0": -938.0,
      "y0": 2840.0,
      "x1": -931.0,
      "y1": 3002.0,
      "len": 16.395030817815346,
      "cum_start": 1113.953113599383
    },
    {
      "x0": -931.0,
      "y0": 3002.0,
      "x1": -920.0,
      "y1": 3187.0,
      "len": 18.738302662823,
      "cum_start": 1130.3481444171982
    },
    {
      "x0": -920.0,
      "y0": 3187.0,
      "x1": -912.0,
      "y1": 3320.0,
      "len": 13.471874957986815,
      "cum_start": 1149.0864470800213
    },
    {
      "x0": -912.0,
      "y0": 3320.0,
      "x1": -913.0,
      "y1": 3439.0,
      "len": 12.032460971351371,
      "cum_start": 1162.558322038008
    },
    {
      "x0": -913.0,
      "y0": 3439.0,
      "x1": -925.0,
      "y1": 3563.0,
      "len": 12.596155840076776,
      "cum_start": 1174.5907830093595
    },
    {
      "x0": -925.0,
      "y0": 3563.0,
      "x1": -958.0,
      "y1": 3705.0,
      "len": 14.740163056986004,
      "cum_start": 1187.1869388494363
    },
    {
      "x0": -958.0,
      "y0": 3705.0,
      "x1": -992.0,
      "y1": 3789.0,
      "len": 9.162555894517604,
      "cum_start": 1201.9271019064224
    },
    {
      "x0": -992.0,
      "y0": 3789.0,
      "x1": -1024.0,
      "y1": 3842.0,
      "len": 6.25981612183403,
      "cum_start": 1211.08965780094
    },
    {
      "x0": -1024.0,
      "y0": 3842.0,
      "x1": -1109.0,
      "y1": 3930.0,
      "len": 12.37053723500885,
      "cum_start": 1217.349473922774
    },
    {
      "x0": -1109.0,
      "y0": 3930.0,
      "x1": -1190.0,
      "y1": 3969.0,
      "len": 9.089742694022597,
      "cum_start": 1229.7200111577827
    },
    {
      "x0": -1190.0,
      "y0": 3969.0,
      "x1": -1270.0,
      "y1": 3983.0,
      "len": 8.21168894489359,
      "cum_start": 1238.8097538518055
    },
    {
      "x0": -1270.0,
      "y0": 3983.0,
      "x1": -1293.0,
      "y1": 3984.0,
      "len": 2.327716587641721,
      "cum_start": 1247.021442796699
    },
    {
      "x0": -1293.0,
      "y0": 3984.0,
      "x1": -1368.0,
      "y1": 3981.0,
      "len": 7.589280208338868,
      "cum_start": 1249.3491593843407
    },
    {
      "x0": -1368.0,
      "y0": 3981.0,
      "x1": -1435.0,
      "y1": 3977.0,
      "len": 6.786401723686166,
      "cum_start": 1256.9384395926795
    },
    {
      "x0": -1435.0,
      "y0": 3977.0,
      "x1": -1433.0,
      "y1": 3976.0,
      "len": 0.22608782131508975,
      "cum_start": 1263.7248413163657
    },
    {
      "x0": -1433.0,
      "y0": 3976.0,
      "x1": -1504.0,
      "y1": 3971.0,
      "len": 7.196556831284278,
      "cum_start": 1263.9509291376808
    },
    {
      "x0": -1504.0,
      "y0": 3971.0,
      "x1": -1617.0,
      "y1": 3972.0,
      "len": 11.425826242624561,
      "cum_start": 1271.1474859689652
    },
    {
      "x0": -1617.0,
      "y0": 3972.0,
      "x1": -1707.0,
      "y1": 3987.0,
      "len": 9.225380502004326,
      "cum_start": 1282.5733122115896
    },
    {
      "x0": -1707.0,
      "y0": 3987.0,
      "x1": -1787.0,
      "y1": 4017.0,
      "len": 8.63880352263123,
      "cum_start": 1291.798692713594
    },
    {
      "x0": -1787.0,
      "y0": 4017.0,
      "x1": -1871.0,
      "y1": 4067.0,
      "len": 9.883943113571322,
      "cum_start": 1300.4374962362253
    },
    {
      "x0": -1871.0,
      "y0": 4067.0,
      "x1": -1923.0,
      "y1": 4109.0,
      "len": 6.758475579111219,
      "cum_start": 1310.3214393497965
    },
    {
      "x0": -1923.0,
      "y0": 4109.0,
      "x1": -2042.0,
      "y1": 4240.0,
      "len": 17.89439044899858,
      "cum_start": 1317.0799149289078
    },
    {
      "x0": -2042.0,
      "y0": 4240.0,
      "x1": -2080.0,
      "y1": 4293.0,
      "len": 6.593862064581087,
      "cum_start": 1334.9743053779064
    },
    {
      "x0": -2080.0,
      "y0": 4293.0,
      "x1": -2133.0,
      "y1": 4386.0,
      "len": 10.822973014535066,
      "cum_start": 1341.5681674424875
    },
    {
      "x0": -2133.0,
      "y0": 4386.0,
      "x1": -2175.0,
      "y1": 4478.0,
      "len": 10.225570006038357,
      "cum_start": 1352.3911404570226
    },
    {
      "x0": -2175.0,
      "y0": 4478.0,
      "x1": -2216.0,
      "y1": 4597.0,
      "len": 12.726153905139105,
      "cum_start": 1362.6167104630608
    },
    {
      "x0": -2216.0,
      "y0": 4597.0,
      "x1": -2248.0,
      "y1": 4724.0,
      "len": 13.242263044132288,
      "cum_start": 1375.3428643682
    },
    {
      "x0": -2248.0,
      "y0": 4724.0,
      "x1": -2277.0,
      "y1": 4882.0,
      "len": 16.24217174239601,
      "cum_start": 1388.5851274123322
    },
    {
      "x0": -2277.0,
      "y0": 4882.0,
      "x1": -2298.0,
      "y1": 5023.0,
      "len": 14.413697064174855,
      "cum_start": 1404.8272991547283
    },
    {
      "x0": -2298.0,
      "y0": 5023.0,
      "x1": -2309.0,
      "y1": 5107.0,
      "len": 8.565715382274236,
      "cum_start": 1419.240996218903
    },
    {
      "x0": -2309.0,
      "y0": 5107.0,
      "x1": -2326.0,
      "y1": 5255.0,
      "len": 15.062607978055185,
      "cum_start": 1427.8067116011773
    },
    {
      "x0": -2326.0,
      "y0": 5255.0,
      "x1": -2348.0,
      "y1": 5460.0,
      "len": 20.846474121895007,
      "cum_start": 1442.8693195792323
    },
    {
      "x0": -2348.0,
      "y0": 5460.0,
      "x1": -2368.0,
      "y1": 5658.0,
      "len": 20.121562064179532,
      "cum_start": 1463.7157937011273
    },
    {
      "x0": -2368.0,
      "y0": 5658.0,
      "x1": -2380.0,
      "y1": 5793.0,
      "len": 13.703607900356134,
      "cum_start": 1483.837355765307
    },
    {
      "x0": -2380.0,
      "y0": 5793.0,
      "x1": -2391.0,
      "y1": 5917.0,
      "len": 12.586818887786702,
      "cum_start": 1497.540963665663
    },
    {
      "x0": -2391.0,
      "y0": 5917.0,
      "x1": -2404.0,
      "y1": 6085.0,
      "len": 17.037183768300928,
      "cum_start": 1510.1277825534498
    },
    {
      "x0": -2404.0,
      "y0": 6085.0,
      "x1": -2416.0,
      "y1": 6256.0,
      "len": 17.332252773933984,
      "cum_start": 1527.1649663217509
    },
    {
      "x0": -2416.0,
      "y0": 6256.0,
      "x1": -2421.0,
      "y1": 6342.0,
      "len": 8.71010483943467,
      "cum_start": 1544.4972190956848
    },
    {
      "x0": -2421.0,
      "y0": 6342.0,
      "x1": -2429.0,
      "y1": 6473.0,
      "len": 13.270026249123571,
      "cum_start": 1553.2073239351196
    },
    {
      "x0": -2429.0,
      "y0": 6473.0,
      "x1": -2437.0,
      "y1": 6620.0,
      "len": 14.88509744657667,
      "cum_start": 1566.4773501842433
    },
    {
      "x0": -2437.0,
      "y0": 6620.0,
      "x1": -2442.0,
      "y1": 6754.0,
      "len": 13.558107940933926,
      "cum_start": 1581.3624476308198
    },
    {
      "x0": -2442.0,
      "y0": 6754.0,
      "x1": -2449.0,
      "y1": 7070.0,
      "len": 31.958455228375573,
      "cum_start": 1594.9205555717538
    },
    {
      "x0": -2449.0,
      "y0": 7070.0,
      "x1": -2445.0,
      "y1": 7394.0,
      "len": 32.76198981689555,
      "cum_start": 1626.8790108001294
    },
    {
      "x0": -2445.0,
      "y0": 7394.0,
      "x1": -2441.0,
      "y1": 7518.0,
      "len": 12.544105386676922,
      "cum_start": 1659.6410006170252
    },
    {
      "x0": -2441.0,
      "y0": 7518.0,
      "x1": -2433.0,
      "y1": 7675.0,
      "len": 15.894793908253787,
      "cum_start": 1672.1851060037022
    },
    {
      "x0": -2433.0,
      "y0": 7675.0,
      "x1": -2418.0,
      "y1": 7896.0,
      "len": 22.396620641506146,
      "cum_start": 1688.079899911956
    },
    {
      "x0": -2418.0,
      "y0": 7896.0,
      "x1": -2396.0,
      "y1": 8135.0,
      "len": 24.267344594174958,
      "cum_start": 1710.476520553462
    },
    {
      "x0": -2396.0,
      "y0": 8135.0,
      "x1": -2382.0,
      "y1": 8263.0,
      "len": 13.019203930051374,
      "cum_start": 1734.7438651476373
    },
    {
      "x0": -2382.0,
      "y0": 8263.0,
      "x1": -2366.0,
      "y1": 8391.0,
      "len": 13.04273972015194,
      "cum_start": 1747.7630690776884
    },
    {
      "x0": -2366.0,
      "y0": 8391.0,
      "x1": -2344.0,
      "y1": 8553.0,
      "len": 16.530096844044934,
      "cum_start": 1760.8058087978407
    },
    {
      "x0": -2344.0,
      "y0": 8553.0,
      "x1": -2296.0,
      "y1": 8843.0,
      "len": 29.72070388612265,
      "cum_start": 1777.3359056418853
    },
    {
      "x0": -2296.0,
      "y0": 8843.0,
      "x1": -2263.0,
      "y1": 9014.0,
      "len": 17.6087436825154,
      "cum_start": 1807.0566095280083
    },
    {
      "x0": -2263.0,
      "y0": 9014.0,
      "x1": -2192.0,
      "y1": 9332.0,
      "len": 32.94449454269613,
      "cum_start": 1824.6653532105236
    },
    {
      "x0": -2192.0,
      "y0": 9332.0,
      "x1": -2113.0,
      "y1": 9661.0,
      "len": 34.21060626407812,
      "cum_start": 1857.6098477532198
    },
    {
      "x0": -2113.0,
      "y0": 9661.0,
      "x1": -2068.0,
      "y1": 9857.0,
      "len": 20.333077203806543,
      "cum_start": 1891.8204540172978
    },
    {
      "x0": -2068.0,
      "y0": 9857.0,
      "x1": -2030.0,
      "y1": 10027.0,
      "len": 17.61280721647681,
      "cum_start": 1912.1535312211045
    },
    {
      "x0": -2030.0,
      "y0": 10027.0,
      "x1": -1996.0,
      "y1": 10167.0,
      "len": 14.56679463964543,
      "cum_start": 1929.7663384375812
    },
    {
      "x0": -1996.0,
      "y0": 10167.0,
      "x1": -1978.0,
      "y1": 10233.0,
      "len": 6.916957276027929,
      "cum_start": 1944.3331330772266
    },
    {
      "x0": -1978.0,
      "y0": 10233.0,
      "x1": -1943.0,
      "y1": 10341.0,
      "len": 11.47893980543442,
      "cum_start": 1951.2500903532543
    },
    {
      "x0": -1943.0,
      "y0": 10341.0,
      "x1": -1897.0,
      "y1": 10437.0,
      "len": 10.763300105408645,
      "cum_start": 1962.7290301586886
    },
    {
      "x0": -1897.0,
      "y0": 10437.0,
      "x1": -1829.0,
      "y1": 10514.0,
      "len": 10.386760931105835,
      "cum_start": 1973.4923302640973
    },
    {
      "x0": -1829.0,
      "y0": 10514.0,
      "x1": -1775.0,
      "y1": 10545.0,
      "len": 6.295642625269232,
      "cum_start": 1983.879091195203
    },
    {
      "x0": -1775.0,
      "y0": 10545.0,
      "x1": -1647.0,
      "y1": 10580.0,
      "len": 13.417126467271542,
      "cum_start": 1990.1747338204725
    },
    {
      "x0": -1647.0,
      "y0": 10580.0,
      "x1": -1549.0,
      "y1": 10607.0,
      "len": 10.277923511598942,
      "cum_start": 2003.5918602877439
    },
    {
      "x0": -1549.0,
      "y0": 10607.0,
      "x1": -1467.0,
      "y1": 10643.0,
      "len": 9.054810187242708,
      "cum_start": 2013.8697837993427
    },
    {
      "x0": -1467.0,
      "y0": 10643.0,
      "x1": -1384.0,
      "y1": 10694.0,
      "len": 9.849751478763995,
      "cum_start": 2022.9245939865855
    },
    {
      "x0": -1384.0,
      "y0": 10694.0,
      "x1": -1283.0,
      "y1": 10780.0,
      "len": 13.412554005545914,
      "cum_start": 2032.7743454653494
    },
    {
      "x0": -1283.0,
      "y0": 10780.0,
      "x1": -1221.0,
      "y1": 10850.0,
      "len": 9.454688853353161,
      "cum_start": 2046.1868994708955
    },
    {
      "x0": -1221.0,
      "y0": 10850.0,
      "x1": -1161.0,
      "y1": 10938.0,
      "len": 10.768997485660519,
      "cum_start": 2055.6415883242485
    },
    {
      "x0": -1161.0,
      "y0": 10938.0,
      "x1": -1096.0,
      "y1": 11065.0,
      "len": 14.425040851126338,
      "cum_start": 2066.4105858099088
    },
    {
      "x0": -1096.0,
      "y0": 11065.0,
      "x1": -1061.0,
      "y1": 11150.0,
      "len": 9.294382065551034,
      "cum_start": 2080.8356266610353
    },
    {
      "x0": -1061.0,
      "y0": 11150.0,
      "x1": -996.0,
      "y1": 11354.0,
      "len": 21.648071224908733,
      "cum_start": 2090.1300087265863
    },
    {
      "x0": -996.0,
      "y0": 11354.0,
      "x1": -959.0,
      "y1": 11496.0,
      "len": 14.836943294073992,
      "cum_start": 2111.778079951495
    },
    {
      "x0": -959.0,
      "y0": 11496.0,
      "x1": -928.0,
      "y1": 11621.0,
      "len": 13.021559423348709,
      "cum_start": 2126.615023245569
    },
    {
      "x0": -928.0,
      "y0": 11621.0,
      "x1": -867.0,
      "y1": 11869.0,
      "len": 25.822554965449616,
      "cum_start": 2139.6365826689175
    },
    {
      "x0": -867.0,
      "y0": 11869.0,
      "x1": -844.0,
      "y1": 11967.0,
      "len": 10.177970504594628,
      "cum_start": 2165.4591376343674
    },
    {
      "x0": -844.0,
      "y0": 11967.0,
      "x1": -812.0,
      "y1": 12105.0,
      "len": 14.323337088405589,
      "cum_start": 2175.637108138962
    },
    {
      "x0": -812.0,
      "y0": 12105.0,
      "x1": -783.0,
      "y1": 12243.0,
      "len": 14.257880298986757,
      "cum_start": 2189.9604452273675
    },
    {
      "x0": -783.0,
      "y0": 12243.0,
      "x1": -752.0,
      "y1": 12412.0,
      "len": 17.372609374538133,
      "cum_start": 2204.2183255263544
    },
    {
      "x0": -752.0,
      "y0": 12412.0,
      "x1": -732.0,
      "y1": 12520.0,
      "len": 11.10549269823411,
      "cum_start": 2221.5909349008925
    },
    {
      "x0": -732.0,
      "y0": 12520.0,
      "x1": -702.0,
      "y1": 12699.0,
      "len": 18.35103468896104,
      "cum_start": 2232.6964275991263
    },
    {
      "x0": -702.0,
      "y0": 12699.0,
      "x1": -656.0,
      "y1": 12995.0,
      "len": 30.287668305237887,
      "cum_start": 2251.0474622880874
    },
    {
      "x0": -656.0,
      "y0": 12995.0,
      "x1": -635.0,
      "y1": 13139.0,
      "len": 14.713784294386693,
      "cum_start": 2281.335130593325
    },
    {
      "x0": -635.0,
      "y0": 13139.0,
      "x1": -614.0,
      "y1": 13299.0,
      "len": 16.31627420977553,
      "cum_start": 2296.0489148877114
    },
    {
      "x0": -614.0,
      "y0": 13299.0,
      "x1": -595.0,
      "y1": 13460.0,
      "len": 16.391600927628502,
      "cum_start": 2312.365189097487
    },
    {
      "x0": -595.0,
      "y0": 13460.0,
      "x1": -579.0,
      "y1": 13637.0,
      "len": 17.96935990836134,
      "cum_start": 2328.7567900251156
    },
    {
      "x0": -579.0,
      "y0": 13637.0,
      "x1": -563.0,
      "y1": 13896.0,
      "len": 26.237294408312778,
      "cum_start": 2346.726149933477
    },
    {
      "x0": -563.0,
      "y0": 13896.0,
      "x1": -557.0,
      "y1": 14082.0,
      "len": 18.816158080015384,
      "cum_start": 2372.9634443417895
    },
    {
      "x0": -557.0,
      "y0": 14082.0,
      "x1": -553.0,
      "y1": 14285.0,
      "len": 20.529222362233977,
      "cum_start": 2391.779602421805
    },
    {
      "x0": -553.0,
      "y0": 14285.0,
      "x1": -552.0,
      "y1": 14455.0,
      "len": 17.188920448191976,
      "cum_start": 2412.308824784039
    },
    {
      "x0": -552.0,
      "y0": 14455.0,
      "x1": -554.0,
      "y1": 14630.0,
      "len": 17.695326307043814,
      "cum_start": 2429.497745232231
    },
    {
      "x0": -554.0,
      "y0": 14630.0,
      "x1": -558.0,
      "y1": 14757.0,
      "len": 12.847280055166376,
      "cum_start": 2447.193071539275
    },
    {
      "x0": -558.0,
      "y0": 14757.0,
      "x1": -565.0,
      "y1": 14884.0,
      "len": 12.860403121804774,
      "cum_start": 2460.0403515944413
    },
    {
      "x0": -565.0,
      "y0": 14884.0,
      "x1": -578.0,
      "y1": 15011.0,
      "len": 12.908010897347975,
      "cum_start": 2472.900754716246
    },
    {
      "x0": -578.0,
      "y0": 15011.0,
      "x1": -610.0,
      "y1": 15216.0,
      "len": 20.978464653856694,
      "cum_start": 2485.808765613594
    },
    {
      "x0": -610.0,
      "y0": 15216.0,
      "x1": -642.0,
      "y1": 15374.0,
      "len": 16.29966188720943,
      "cum_start": 2506.787230267451
    },
    {
      "x0": -642.0,
      "y0": 15374.0,
      "x1": -688.0,
      "y1": 15577.0,
      "len": 21.04560681082371,
      "cum_start": 2523.0868921546607
    },
    {
      "x0": -688.0,
      "y0": 15577.0,
      "x1": -724.0,
      "y1": 15730.0,
      "len": 15.892220998373594,
      "cum_start": 2544.132498965484
    },
    {
      "x0": -724.0,
      "y0": 15730.0,
      "x1": -734.0,
      "y1": 15775.0,
      "len": 4.660919839739435,
      "cum_start": 2560.024719963858
    },
    {
      "x0": -734.0,
      "y0": 15775.0,
      "x1": -805.0,
      "y1": 16082.0,
      "len": 31.85993768232456,
      "cum_start": 2564.6856398035975
    },
    {
      "x0": -805.0,
      "y0": 16082.0,
      "x1": -836.0,
      "y1": 16231.0,
      "len": 15.387929761072511,
      "cum_start": 2596.545577485922
    },
    {
      "x0": -836.0,
      "y0": 16231.0,
      "x1": -851.0,
      "y1": 16305.0,
      "len": 7.634273017136203,
      "cum_start": 2611.9335072469944
    },
    {
      "x0": -851.0,
      "y0": 16305.0,
      "x1": -875.0,
      "y1": 16456.0,
      "len": 15.459183599350332,
      "cum_start": 2619.5677802641303
    },
    {
      "x0": -875.0,
      "y0": 16456.0,
      "x1": -880.0,
      "y1": 16523.0,
      "len": 6.793177211037202,
      "cum_start": 2635.026963863481
    },
    {
      "x0": -880.0,
      "y0": 16523.0,
      "x1": -878.0,
      "y1": 16585.0,
      "len": 6.272052693338461,
      "cum_start": 2641.820141074518
    },
    {
      "x0": -878.0,
      "y0": 16585.0,
      "x1": -867.0,
      "y1": 16634.0,
      "len": 5.07767275102175,
      "cum_start": 2648.0921937678563
    },
    {
      "x0": -867.0,
      "y0": 16634.0,
      "x1": -841.0,
      "y1": 16687.0,
      "len": 5.96888975891344,
      "cum_start": 2653.1698665188783
    },
    {
      "x0": -841.0,
      "y0": 16687.0,
      "x1": -814.0,
      "y1": 16715.0,
      "len": 3.9328884692759076,
      "cum_start": 2659.138756277792
    },
    {
      "x0": -814.0,
      "y0": 16715.0,
      "x1": -784.0,
      "y1": 16736.0,
      "len": 3.702597943388731,
      "cum_start": 2663.0716447470677
    },
    {
      "x0": -784.0,
      "y0": 16736.0,
      "x1": -756.0,
      "y1": 16748.0,
      "len": 3.080109489444155,
      "cum_start": 2666.774242690456
    },
    {
      "x0": -756.0,
      "y0": 16748.0,
      "x1": -693.0,
      "y1": 16760.0,
      "len": 6.484425745137765,
      "cum_start": 2669.8543521799
    },
    {
      "x0": -693.0,
      "y0": 16760.0,
      "x1": -653.0,
      "y1": 16755.0,
      "len": 4.075856162547481,
      "cum_start": 2676.3387779250384
    },
    {
      "x0": -653.0,
      "y0": 16755.0,
      "x1": -629.0,
      "y1": 16747.0,
      "len": 2.557891705529479,
      "cum_start": 2680.414634087586
    },
    {
      "x0": -629.0,
      "y0": 16747.0,
      "x1": -587.0,
      "y1": 16721.0,
      "len": 4.994443216028983,
      "cum_start": 2682.9725257931154
    },
    {
      "x0": -587.0,
      "y0": 16721.0,
      "x1": -560.0,
      "y1": 16693.0,
      "len": 3.9328884692759076,
      "cum_start": 2687.966969009144
    },
    {
      "x0": -560.0,
      "y0": 16693.0,
      "x1": -540.0,
      "y1": 16666.0,
      "len": 3.397340978682224,
      "cum_start": 2691.89985747842
    },
    {
      "x0": -540.0,
      "y0": 16666.0,
      "x1": -516.0,
      "y1": 16626.0,
      "len": 4.7165192592139515,
      "cum_start": 2695.2971984571022
    },
    {
      "x0": -516.0,
      "y0": 16626.0,
      "x1": -501.0,
      "y1": 16596.0,
      "len": 3.391317319726346,
      "cum_start": 2700.0137177163165
    },
    {
      "x0": -501.0,
      "y0": 16596.0,
      "x1": -476.0,
      "y1": 16533.0,
      "len": 6.853109357635207,
      "cum_start": 2703.405035036043
    },
    {
      "x0": -476.0,
      "y0": 16533.0,
      "x1": -448.0,
      "y1": 16439.0,
      "len": 9.916986057771565,
      "cum_start": 2710.258144393678
    },
    {
      "x0": -448.0,
      "y0": 16439.0,
      "x1": -427.0,
      "y1": 16337.0,
      "len": 10.529480504376822,
      "cum_start": 2720.1751304514496
    },
    {
      "x0": -427.0,
      "y0": 16337.0,
      "x1": -414.0,
      "y1": 16235.0,
      "len": 10.396598744384365,
      "cum_start": 2730.7046109558264
    },
    {
      "x0": -414.0,
      "y0": 16235.0,
      "x1": -403.0,
      "y1": 16113.0,
      "len": 12.385403689180214,
      "cum_start": 2741.101209700211
    },
    {
      "x0": -403.0,
      "y0": 16113.0,
      "x1": -387.0,
      "y1": 15923.0,
      "len": 19.278809591576323,
      "cum_start": 2753.486613389391
    },
    {
      "x0": -387.0,
      "y0": 15923.0,
      "x1": -376.0,
      "y1": 15837.0,
      "len": 8.766261906338741,
      "cum_start": 2772.7654229809677
    },
    {
      "x0": -376.0,
      "y0": 15837.0,
      "x1": -356.0,
      "y1": 15729.0,
      "len": 11.10549269823411,
      "cum_start": 2781.5316848873063
    },
    {
      "x0": -356.0,
      "y0": 15729.0,
      "x1": -337.0,
      "y1": 15648.0,
      "len": 8.412168517084774,
      "cum_start": 2792.6371775855405
    },
    {
      "x0": -337.0,
      "y0": 15648.0,
      "x1": -285.0,
      "y1": 15481.0,
      "len": 17.684924089504552,
      "cum_start": 2801.0493461026253
    },
    {
      "x0": -285.0,
      "y0": 15481.0,
      "x1": -215.0,
      "y1": 15297.0,
      "len": 19.904975174132147,
      "cum_start": 2818.7342701921298
    },
    {
      "x0": -215.0,
      "y0": 15297.0,
      "x1": -174.0,
      "y1": 15198.0,
      "len": 10.834302019396537,
      "cum_start": 2838.639245366262
    },
    {
      "x0": -174.0,
      "y0": 15198.0,
      "x1": -117.0,
      "y1": 15061.0,
      "len": 15.003103328892545,
      "cum_start": 2849.4735473856585
    },
    {
      "x0": -117.0,
      "y0": 15061.0,
      "x1": -72.0,
      "y1": 14956.0,
      "len": 11.550410585415582,
      "cum_start": 2864.476650714551
    },
    {
      "x0": -72.0,
      "y0": 14956.0,
      "x1": 9.0,
      "y1": 14764.0,
      "len": 21.06988087519076,
      "cum_start": 2876.0270612999666
    },
    {
      "x0": 9.0,
      "y0": 14764.0,
      "x1": 67.0,
      "y1": 14628.0,
      "len": 14.949175672400846,
      "cum_start": 2897.0969421751574
    },
    {
      "x0": 67.0,
      "y0": 14628.0,
      "x1": 120.0,
      "y1": 14503.0,
      "len": 13.727832080303655,
      "cum_start": 2912.0461178475584
    },
    {
      "x0": 120.0,
      "y0": 14503.0,
      "x1": 215.0,
      "y1": 14285.0,
      "len": 24.04388440310811,
      "cum_start": 2925.773949927862
    },
    {
      "x0": 215.0,
      "y0": 14285.0,
      "x1": 298.0,
      "y1": 14095.0,
      "len": 20.963840077565717,
      "cum_start": 2949.81783433097
    },
    {
      "x0": 298.0,
      "y0": 14095.0,
      "x1": 368.0,
      "y1": 13935.0,
      "len": 17.658023331526213,
      "cum_start": 2970.7816744085358
    },
    {
      "x0": 368.0,
      "y0": 13935.0,
      "x1": 409.0,
      "y1": 13841.0,
      "len": 10.369029346025023,
      "cum_start": 2988.439697740062
    },
    {
      "x0": 409.0,
      "y0": 13841.0,
      "x1": 526.0,
      "y1": 13568.0,
      "len": 30.031067522080512,
      "cum_start": 2998.8087270860874
    },
    {
      "x0": 526.0,
      "y0": 13568.0,
      "x1": 591.0,
      "y1": 13414.0,
      "len": 16.90102870266918,
      "cum_start": 3028.8397946081677
    },
    {
      "x0": 591.0,
      "y0": 13414.0,
      "x1": 690.0,
      "y1": 13172.0,
      "len": 26.436811577691913,
      "cum_start": 3045.740823310837
    },
    {
      "x0": 690.0,
      "y0": 13172.0,
      "x1": 749.0,
      "y1": 13028.0,
      "len": 15.734477927580533,
      "cum_start": 3072.1776348885287
    },
    {
      "x0": 749.0,
      "y0": 13028.0,
      "x1": 835.0,
      "y1": 12809.0,
      "len": 23.789123430834092,
      "cum_start": 3087.9121128161096
    },
    {
      "x0": 835.0,
      "y0": 12809.0,
      "x1": 913.0,
      "y1": 12601.0,
      "len": 22.4608891588412,
      "cum_start": 3111.7012362469436
    },
    {
      "x0": 913.0,
      "y0": 12601.0,
      "x1": 1017.0,
      "y1": 12297.0,
      "len": 32.48623168859421,
      "cum_start": 3134.162125405785
    },
    {
      "x0": 1017.0,
      "y0": 12297.0,
      "x1": 1060.0,
      "y1": 12159.0,
      "len": 14.614789643862505,
      "cum_start": 3166.648357094379
    },
    {
      "x0": 1060.0,
      "y0": 12159.0,
      "x1": 1107.0,
      "y1": 12003.0,
      "len": 16.473410908055563,
      "cum_start": 3181.2631467382416
    },
    {
      "x0": 1107.0,
      "y0": 12003.0,
      "x1": 1165.0,
      "y1": 11798.0,
      "len": 21.541080014992573,
      "cum_start": 3197.736557646297
    },
    {
      "x0": 1165.0,
      "y0": 11798.0,
      "x1": 1229.0,
      "y1": 11560.0,
      "len": 24.91893977279539,
      "cum_start": 3219.2776376612896
    },
    {
      "x0": 1229.0,
      "y0": 11560.0,
      "x1": 1325.0,
      "y1": 11175.0,
      "len": 40.11909118531786,
      "cum_start": 3244.1965774340847
    },
    {
      "x0": 1325.0,
      "y0": 11175.0,
      "x1": 1391.0,
      "y1": 10899.0,
      "len": 28.693029779819778,
      "cum_start": 3284.315668619403
    },
    {
      "x0": 1391.0,
      "y0": 10899.0,
      "x1": 1426.0,
      "y1": 10752.0,
      "len": 15.27858606738129,
      "cum_start": 3313.0086983992223
    },
    {
      "x0": 1426.0,
      "y0": 10752.0,
      "x1": 1479.0,
      "y1": 10523.0,
      "len": 23.76612121412313,
      "cum_start": 3328.287284466604
    },
    {
      "x0": 1479.0,
      "y0": 10523.0,
      "x1": 1553.0,
      "y1": 10210.0,
      "len": 32.51972906207191,
      "cum_start": 3352.053405680727
    },
    {
      "x0": 1553.0,
      "y0": 10210.0,
      "x1": 1560.0,
      "y1": 10177.0,
      "len": 3.4108553165940796,
      "cum_start": 3384.5731347427986
    },
    {
      "x0": 1560.0,
      "y0": 10177.0,
      "x1": 1614.0,
      "y1": 9945.0,
      "len": 24.084455506458948,
      "cum_start": 3387.983990059393
    },
    {
      "x0": 1614.0,
      "y0": 9945.0,
      "x1": 1649.0,
      "y1": 9795.0,
      "len": 15.573824529752919,
      "cum_start": 3412.0684455658516
    },
    {
      "x0": 1649.0,
      "y0": 9795.0,
      "x1": 1692.0,
      "y1": 9612.0,
      "len": 19.006981405479543,
      "cum_start": 3427.642270095604
    },
    {
      "x0": 1692.0,
      "y0": 9612.0,
      "x1": 1723.0,
      "y1": 9478.0,
      "len": 13.906514679447714,
      "cum_start": 3446.6492515010837
    },
    {
      "x0": 1723.0,
      "y0": 9478.0,
      "x1": 1782.0,
      "y1": 9227.0,
      "len": 26.070190499199338,
      "cum_start": 3460.555766180531
    },
    {
      "x0": 1782.0,
      "y0": 9227.0,
      "x1": 1813.0,
      "y1": 9093.0,
      "len": 13.906514679447714,
      "cum_start": 3486.6259566797303
    },
    {
      "x0": 1813.0,
      "y0": 9093.0,
      "x1": 1867.0,
      "y1": 8858.0,
      "len": 24.379983941921523,
      "cum_start": 3500.5324713591776
    },
    {
      "x0": 1867.0,
      "y0": 8858.0,
      "x1": 1906.0,
      "y1": 8690.0,
      "len": 17.438099576264797,
      "cum_start": 3524.912455301099
    },
    {
      "x0": 1906.0,
      "y0": 8690.0,
      "x1": 1937.0,
      "y1": 8555.0,
      "len": 14.005041069138056,
      "cum_start": 3542.3505548773637
    },
    {
      "x0": 1937.0,
      "y0": 8555.0,
      "x1": 1967.0,
      "y1": 8420.0,
      "len": 13.982759519218304,
      "cum_start": 3556.3555959465016
    },
    {
      "x0": 1967.0,
      "y0": 8420.0,
      "x1": 2006.0,
      "y1": 8251.0,
      "len": 17.536605008106743,
      "cum_start": 3570.3383554657203
    },
    {
      "x0": 2006.0,
      "y0": 8251.0,
      "x1": 2071.0,
      "y1": 7964.0,
      "len": 29.753363443459165,
      "cum_start": 3587.8749604738273
    },
    {
      "x0": 2071.0,
      "y0": 7964.0,
      "x1": 2102.0,
      "y1": 7832.0,
      "len": 13.709574746728416,
      "cum_start": 3617.6283239172863
    },
    {
      "x0": 2102.0,
      "y0": 7832.0,
      "x1": 2141.0,
      "y1": 7664.0,
      "len": 17.438099576264797,
      "cum_start": 3631.337898664015
    },
    {
      "x0": 2141.0,
      "y0": 7664.0,
      "x1": 2165.0,
      "y1": 7563.0,
      "len": 10.496417776173562,
      "cum_start": 3648.77599824028
    },
    {
      "x0": 2165.0,
      "y0": 7563.0,
      "x1": 2201.0,
      "y1": 7412.0,
      "len": 15.695445797516896,
      "cum_start": 3659.2724160164535
    },
    {
      "x0": 2201.0,
      "y0": 7412.0,
      "x1": 2245.0,
      "y1": 7229.0,
      "len": 19.030364036967946,
      "cum_start": 3674.9678618139706
    },
    {
      "x0": 2245.0,
      "y0": 7229.0,
      "x1": 2297.0,
      "y1": 7014.0,
      "len": 22.365331338900198,
      "cum_start": 3693.9982258509385
    },
    {
      "x0": 2297.0,
      "y0": 7014.0,
      "x1": 2348.0,
      "y1": 6799.0,
      "len": 22.341778407684625,
      "cum_start": 3716.363557189839
    },
    {
      "x0": 2348.0,
      "y0": 6799.0,
      "x1": 2410.0,
      "y1": 6537.0,
      "len": 27.222325672956096,
      "cum_start": 3738.7053355975236
    },
    {
      "x0": 2410.0,
      "y0": 6537.0,
      "x1": 2437.0,
      "y1": 6423.0,
      "len": 11.845362155270976,
      "cum_start": 3765.9276612704793
    },
    {
      "x0": 2437.0,
      "y0": 6423.0,
      "x1": 2486.0,
      "y1": 6218.0,
      "len": 21.31134073268783,
      "cum_start": 3777.7730234257506
    },
    {
      "x0": 2486.0,
      "y0": 6218.0,
      "x1": 2513.0,
      "y1": 6103.0,
      "len": 11.943772594306148,
      "cum_start": 3799.0843641584383
    },
    {
      "x0": 2513.0,
      "y0": 6103.0,
      "x1": 2558.0,
      "y1": 5907.0,
      "len": 20.333077203806543,
      "cum_start": 3811.028136752745
    },
    {
      "x0": 2558.0,
      "y0": 5907.0,
      "x1": 2593.0,
      "y1": 5725.0,
      "len": 18.739121006742224,
      "cum_start": 3831.3612139565516
    },
    {
      "x0": 2593.0,
      "y0": 5725.0,
      "x1": 2605.0,
      "y1": 5550.0,
      "len": 17.735721377921816,
      "cum_start": 3850.100334963294
    },
    {
      "x0": 2605.0,
      "y0": 5550.0,
      "x1": 2585.0,
      "y1": 5439.0,
      "len": 11.403884050522763,
      "cum_start": 3867.8360563412157
    },
    {
      "x0": 2585.0,
      "y0": 5439.0,
      "x1": 2537.0,
      "y1": 5337.0,
      "len": 11.398055562687228,
      "cum_start": 3879.2399403917384
    },
    {
      "x0": 2537.0,
      "y0": 5337.0,
      "x1": 2484.0,
      "y1": 5252.0,
      "len": 10.12812878443237,
      "cum_start": 3890.6379959544256
    },
    {
      "x0": 2484.0,
      "y0": 5252.0,
      "x1": 2452.0,
      "y1": 5194.0,
      "len": 6.697696686644647,
      "cum_start": 3900.766124738858
    },
    {
      "x0": 2452.0,
      "y0": 5194.0,
      "x1": 2421.0,
      "y1": 5118.0,
      "len": 8.298993803515769,
      "cum_start": 3907.4638214255024
    },
    {
      "x0": 2421.0,
      "y0": 5118.0,
      "x1": 2397.0,
      "y1": 4985.0,
      "len": 13.664759890514192,
      "cum_start": 3915.762815229018
    },
    {
      "x0": 2397.0,
      "y0": 4985.0,
      "x1": 2395.0,
      "y1": 4875.0,
      "len": 11.123888425101502,
      "cum_start": 3929.427575119532
    },
    {
      "x0": 2395.0,
      "y0": 4875.0,
      "x1": 2405.0,
      "y1": 4732.0,
      "len": 14.493975161134948,
      "cum_start": 3940.5514635446334
    },
    {
      "x0": 2405.0,
      "y0": 4732.0,
      "x1": 2416.0,
      "y1": 4648.0,
      "len": 8.565715382274236,
      "cum_start": 3955.045438705768
    },
    {
      "x0": 2416.0,
      "y0": 4648.0,
      "x1": 2435.0,
      "y1": 4540.0,
      "len": 11.087527478547438,
      "cum_start": 3963.6111540880415
    },
    {
      "x0": 2435.0,
      "y0": 4540.0,
      "x1": 2452.0,
      "y1": 4459.0,
      "len": 8.368304071757635,
      "cum_start": 3974.698681566589
    },
    {
      "x0": 2452.0,
      "y0": 4459.0,
      "x1": 2472.0,
      "y1": 4376.0,
      "len": 8.632292381293764,
      "cum_start": 3983.0669856383465
    },
    {
      "x0": 2472.0,
      "y0": 4376.0,
      "x1": 2500.0,
      "y1": 4270.0,
      "len": 11.085222139614412,
      "cum_start": 3991.6992780196406
    },
    {
      "x0": 2500.0,
      "y0": 4270.0,
      "x1": 2546.0,
      "y1": 4105.0,
      "len": 17.31927157918625,
      "cum_start": 4002.784500159255
    },
    {
      "x0": 2546.0,
      "y0": 4105.0,
      "x1": 2573.0,
      "y1": 4015.0,
      "len": 9.500531998989299,
      "cum_start": 4020.1037717384415
    },
    {
      "x0": 2573.0,
      "y0": 4015.0,
      "x1": 2617.0,
      "y1": 3864.0,
      "len": 15.902510140226521,
      "cum_start": 4029.6043037374307
    },
    {
      "x0": 2617.0,
      "y0": 3864.0,
      "x1": 2661.0,
      "y1": 3707.0,
      "len": 16.485817922360418,
      "cum_start": 4045.506813877657
    },
    {
      "x0": 2661.0,
      "y0": 3707.0,
      "x1": 2735.0,
      "y1": 3431.0,
      "len": 28.891865211608497,
      "cum_start": 4061.9926318000175
    },
    {
      "x0": 2735.0,
      "y0": 3431.0,
      "x1": 2782.0,
      "y1": 3249.0,
      "len": 19.00563670191815,
      "cum_start": 4090.8844970116256
    },
    {
      "x0": 2782.0,
      "y0": 3249.0,
      "x1": 2823.0,
      "y1": 3088.0,
      "len": 16.798188192440296,
      "cum_start": 4109.890133713544
    },
    {
      "x0": 2823.0,
      "y0": 3088.0,
      "x1": 2864.0,
      "y1": 2925.0,
      "len": 16.9942261268518,
      "cum_start": 4126.688321905985
    },
    {
      "x0": 2864.0,
      "y0": 2925.0,
      "x1": 2906.0,
      "y1": 2759.0,
      "len": 17.31307257771512,
      "cum_start": 4143.682548032836
    },
    {
      "x0": 2906.0,
      "y0": 2759.0,
      "x1": 2968.0,
      "y1": 2520.0,
      "len": 24.965050891853178,
      "cum_start": 4160.995620610551
    },
    {
      "x0": 2968.0,
      "y0": 2520.0,
      "x1": 3203.0,
      "y1": 1624.0,
      "len": 93.65828193208567,
      "cum_start": 4185.960671502405
    },
    {
      "x0": 3203.0,
      "y0": 1624.0,
      "x1": 3263.0,
      "y1": 1377.0,
      "len": 25.70032860374738,
      "cum_start": 4279.618953434489
    },
    {
      "x0": 3263.0,
      "y0": 1377.0,
      "x1": 3312.0,
      "y1": 1149.0,
      "len": 23.579344794853014,
      "cum_start": 4305.319282038237
    },
    {
      "x0": 3312.0,
      "y0": 1149.0,
      "x1": 3349.0,
      "y1": 944.0,
      "len": 21.062358907217824,
      "cum_start": 4328.898626833091
    },
    {
      "x0": 3349.0,
      "y0": 944.0,
      "x1": 3365.0,
      "y1": 836.0,
      "len": 11.039014259690827,
      "cum_start": 4349.960985740308
    }
  ],
  "length": 4361
}